{"cameraMode":{"drawMode":0,"name":"Shaded","section":"Shading Mode"},"sceneLighting":true,"audioPlay":false,"sceneViewState":{"m_AlwaysRefresh":false,"showFog":true,"showSkybox":true,"showFlares":true,"showImageEffects":true,"showParticleSystems":true,"showVisualEffectGraphs":true,"m_FxEnabled":true},"in2DMode":false,"pivot":{"x":0.6555742025375366,"y":2.1813862323760988,"z":3.04878306388855},"rotation":{"x":-0.05272071808576584,"y":0.9227654933929443,"z":-0.13645276427268983,"w":-0.3565264046192169},"size":1.2124356031417847,"orthographic":false}